ls_python/__init__.py
ls_python/convectionDemo.py
ls_python/gridHandler.py
ls_python/matplotlib3d_example.py
ls_python/normalVelocityDemo.py
ls_python/odeCFL.py
ls_python/options.py
ls_python/pyvista3d_example.py
ls_python/pyvista3d_example_terrain.py
ls_python/read_data.py
ls_python/spatialDerivative.py
ls_python/terms.py
ls_python-0.1.dist-info/LICENSE
ls_python-0.1.dist-info/METADATA
ls_python-0.1.dist-info/WHEEL
ls_python-0.1.dist-info/top_level.txt
ls_python-0.1.dist-info/RECORD
